geostructures/__init__.py
geostructures/_base.py
geostructures/_const.py
geostructures/_geometry.py
geostructures/_version.py
geostructures/calc.py
geostructures/collections.py
geostructures/conversion.py
geostructures/coordinates.py
geostructures/geohash.py
geostructures/multistructures.py
geostructures/parsers.py
geostructures/py.typed
geostructures/structures.py
geostructures/time.py
geostructures/typing.py
geostructures/utils/__init__.py
geostructures/utils/agg_functions.py
geostructures/utils/conditional_imports.py
geostructures/utils/functions.py
geostructures/utils/logging.py
geostructures-0.13.2.dist-info/licenses/LICENSE
geostructures-0.13.2.dist-info/METADATA
geostructures-0.13.2.dist-info/WHEEL
geostructures-0.13.2.dist-info/top_level.txt
geostructures-0.13.2.dist-info/RECORD
