Metadata-Version: 2.4
Name: geostructures
Version: 0.13.2
Summary: A lightweight implementation of shapes drawn across a geo-temporal plane.
Author: Carl Best
Project-URL: Homepage, https://github.com/ccbest/geostructures
Classifier: Operating System :: OS Independent
Classifier: Programming Language :: Python :: 3
Requires-Python: >=3.9
License-File: LICENSE
Requires-Dist: numpy<3,>=2
Requires-Dist: pydantic<3,>=2
Provides-Extra: dev
Requires-Dist: coverage>=5.5; extra == "dev"
Requires-Dist: flake8; extra == "dev"
Requires-Dist: geostructures[df,h3,kml,mgrs,proj,shapefile,shapely]; extra == "dev"
Requires-Dist: mypy; extra == "dev"
Requires-Dist: pylint; extra == "dev"
Requires-Dist: pytest; extra == "dev"
Requires-Dist: pandas-stubs; extra == "dev"
Requires-Dist: types-geopandas; extra == "dev"
Requires-Dist: types-shapely; extra == "dev"
Provides-Extra: df
Requires-Dist: geopandas<2,>=1; extra == "df"
Requires-Dist: pandas<3,>=2; extra == "df"
Provides-Extra: h3
Requires-Dist: h3<5,>=4.1; extra == "h3"
Provides-Extra: kml
Requires-Dist: fastkml<2,>=1; extra == "kml"
Provides-Extra: mgrs
Requires-Dist: mgrs<2,>=1.4.5; extra == "mgrs"
Provides-Extra: proj
Requires-Dist: pyproj<4,>=3.6; extra == "proj"
Provides-Extra: shapefile
Requires-Dist: pyshp<3,>=2.3.1; extra == "shapefile"
Provides-Extra: shapely
Requires-Dist: shapely>=2.0.7; extra == "shapely"
Dynamic: license-file
